adafruit_circuitpython_pm25-2.1.22.dist-info/licenses/LICENSE
adafruit_pm25/__init__.py
adafruit_pm25/i2c.py
adafruit_pm25/uart.py
adafruit_circuitpython_pm25-2.1.22.dist-info/METADATA
adafruit_circuitpython_pm25-2.1.22.dist-info/WHEEL
adafruit_circuitpython_pm25-2.1.22.dist-info/top_level.txt
adafruit_circuitpython_pm25-2.1.22.dist-info/RECORD
