Metadata-Version: 2.4
Name: adafruit-circuitpython-pm25
Version: 2.1.22
Summary: CircuitPython library for PM2.5 Air Quality Sensors
Author-email: Adafruit Industries <circuitpython@adafruit.com>
License: MIT
Project-URL: Homepage, https://github.com/adafruit/Adafruit_CircuitPython_PM25
Keywords: adafruit,blinka,circuitpython,micropython,pm25,AQI,PM2.5,Air,Quality
Classifier: Intended Audience :: Developers
Classifier: Topic :: Software Development :: Libraries
Classifier: Topic :: Software Development :: Embedded Systems
Classifier: Topic :: System :: Hardware
Classifier: License :: OSI Approved :: MIT License
Classifier: Programming Language :: Python :: 3
License-File: LICENSE
Requires-Dist: Adafruit-Blinka
Requires-Dist: adafruit-circuitpython-busdevice
Provides-Extra: optional
Requires-Dist: pyserial; extra == "optional"
Dynamic: license-file
